LICENSE
README.md
setup.py
neurosdk/__cmn_types.py
neurosdk/__init__.py
neurosdk/__utils.py
neurosdk/amp_sensor.py
neurosdk/brainbit_2_sensor.py
neurosdk/brainbit_black_sensor.py
neurosdk/brainbit_sensor.py
neurosdk/callibri_sensor.py
neurosdk/cmn_types.py
neurosdk/electrode_sensor.py
neurosdk/envelope_sensor.py
neurosdk/fpg_sensor.py
neurosdk/headband_sensor.py
neurosdk/headphones_2_sensor.py
neurosdk/mems_sensor.py
neurosdk/neuro_eeg_sensor.py
neurosdk/neuro_lib_load.py
neurosdk/neuro_smart_sensor.py
neurosdk/photo_stim_sensor.py
neurosdk/resist_sensor.py
neurosdk/respiration_sensor.py
neurosdk/sample.py
neurosdk/scanner.py
neurosdk/sensor.py
neurosdk/signal_resist_sensor.py
neurosdk/signal_sensor.py
neurosdk/libs/macos/libneurosdk2.dylib
neurosdk/libs/win/neurosdk2-x32.dll
neurosdk/libs/win/neurosdk2-x64.dll
pyneurosdk2.egg-info/PKG-INFO
pyneurosdk2.egg-info/SOURCES.txt
pyneurosdk2.egg-info/dependency_links.txt
pyneurosdk2.egg-info/top_level.txt