Metadata-Version: 2.1
Name: pyneurosdk2
Version: 1.0.15
Summary: Python wrapper for NeuroSDK2
Home-page: https://gitlab.com/brainbit-inc/brainbit-sdk
Author: Brainbit Inc.
Author-email: support@brainbit.com
License: MIT
Classifier: Programming Language :: Python :: 3
Classifier: License :: OSI Approved :: MIT License
Classifier: Operating System :: Microsoft :: Windows
Classifier: Operating System :: POSIX :: Linux
Classifier: Operating System :: MacOS
Classifier: Intended Audience :: Developers
Requires-Python: >=3.7
License-File: LICENSE
